base64c/__init__.py
base64c/base64c.c
base64c/base64c.cpython-310-darwin.so
base64c/base64c.pyi
cbase64-0.0.9.dist-info/LICENSE
cbase64-0.0.9.dist-info/METADATA
cbase64-0.0.9.dist-info/WHEEL
cbase64-0.0.9.dist-info/top_level.txt
cbase64-0.0.9.dist-info/RECORD
