Metadata-Version: 2.1
Name: cbase64
Version: 0.0.9
Summary: Fast Base64 encoding/decoding with SSE2 and VSX optimizations
Home-page: https://github.com/obahamonde/base64c
Author: Oscar Bahamonde
Author-email: Oscar Bahamonde <oscar.bahamonde@indiecloud.co>
License: MIT
Classifier: Development Status :: 4 - Beta
Classifier: Intended Audience :: Developers
Classifier: License :: OSI Approved :: MIT License
Classifier: Programming Language :: Python :: 3
Classifier: Programming Language :: Python :: 3.6
Classifier: Programming Language :: Python :: 3.7
Classifier: Programming Language :: Python :: 3.8
Classifier: Programming Language :: Python :: 3.9
Classifier: Programming Language :: Python :: 3.10
Classifier: Programming Language :: C
Classifier: Operating System :: OS Independent
Classifier: Topic :: Software Development :: Libraries :: Python Modules
Classifier: Topic :: Utilities
Requires-Python: >=3.8
License-File: LICENSE
Provides-Extra: dev
Requires-Dist: pytest; extra == "dev"
Requires-Dist: pyright; extra == "dev"
Requires-Dist: isort; extra == "dev"
Requires-Dist: black; extra == "dev"
Requires-Dist: pytest-html; extra == "dev"
Requires-Dist: setuptools; extra == "dev"
